Metadata-Version: 1.0
Name: dsnd-by-cs
Version: 0.1
Summary: Gaussian and Binomial distributions
Home-page: UNKNOWN
Author: Camila Santos
Author-email: UNKNOWN
License: UNKNOWN
Platform: UNKNOWN
